tile/__init__.py
tile/__main__.py
tile/__version__.py
tile/cli.py
tile/constants.py
tile/io.py
tile/node.py
tile/random_input_generator.py
tile/tree_algorithms.py
tile/tree_parser.py
tile-1.0.0a9.dist-info/entry_points.txt
tile-1.0.0a9.dist-info/LICENSE
tile-1.0.0a9.dist-info/WHEEL
tile-1.0.0a9.dist-info/METADATA
tile-1.0.0a9.dist-info/RECORD
