Metadata-Version: 2.1
Name: tile
Version: 1.0.0a9
Summary: Syntax and config generator for tiling window managers
Home-page: https://github.com/ViliamV/tile
License: MIT
Keywords: i3,sway
Author: Viliam Valent
Author-email: tile@viliamvalent.com
Requires-Python: >=3.7,<4.0
Classifier: License :: OSI Approved :: MIT License
Classifier: Programming Language :: Python :: 3
Classifier: Programming Language :: Python :: 3.7
Classifier: Programming Language :: Python :: 3.8
Project-URL: Repository, https://github.com/ViliamV/tile
